modxlib/__init__.py
modxlib/modxlib.py
modxlib-0.4.0.dist-info/LICENSE
modxlib-0.4.0.dist-info/METADATA
modxlib-0.4.0.dist-info/WHEEL
modxlib-0.4.0.dist-info/top_level.txt
modxlib-0.4.0.dist-info/RECORD
