Metadata-Version: 2.1
Name: modxlib
Version: 0.4.0
Summary: Package of utilities for CTPS Model Data Explorer
Home-page: https://github.com/CTPSSTAFF/modxlib
Author: Ben Krepp
Author-email: bkrepp@ctps.org
License: UNKNOWN
Project-URL: Bug Tracker, https://github.com/CTPSSTAFF/modxlib/issues
Platform: UNKNOWN
Classifier: Programming Language :: Python :: 3
Classifier: License :: OSI Approved :: GNU General Public License v3 (GPLv3)
Classifier: Operating System :: OS Independent
Requires-Python: >=3.6
License-File: LICENSE
